measureit2/__init__.py
measureit2/benchmark.py
measureit2/dot_product/__init__.py
measureit2/dot_product/naive.py
measureit2/dot_product/wrap_numpy.py
measureit2/dot_product/wrap_pytorch.py
measureit2-0.1.1.dist-info/METADATA
measureit2-0.1.1.dist-info/WHEEL
measureit2-0.1.1.dist-info/top_level.txt
measureit2-0.1.1.dist-info/RECORD
