Metadata-Version: 2.1
Name: measureit2
Version: 0.1.1
Summary: 4 Naive native python ways to compute dot product are currently supported. Benchmarking TBA soon.
Author: Dhananjayan Sudhakar
Author-email: vvandhiyadhevan@gmail.com
